Connect_to_Server/Connection.py
Connect_to_Server/__init__.py
Connect_to_Server_CPS-0.1.1.dist-info/METADATA
Connect_to_Server_CPS-0.1.1.dist-info/WHEEL
Connect_to_Server_CPS-0.1.1.dist-info/top_level.txt
Connect_to_Server_CPS-0.1.1.dist-info/RECORD
