Metadata-Version: 2.1
Name: Connect-to-Server-CPS
Version: 0.1.1
Summary: Demo library
Home-page: https://www.in.tum.de/en/i06/home/
Author: Houman Heidarabadi
Author-email: hooman.heidarabadi@gmail.com
License: UNKNOWN
Platform: UNKNOWN
Classifier: Intended Audience :: Developers
Classifier: License :: OSI Approved :: MIT License
Classifier: Programming Language :: Python
Classifier: Programming Language :: Python :: 3
Classifier: Programming Language :: Python :: 3.6
Classifier: Programming Language :: Python :: 3.7
Classifier: Programming Language :: Python :: 3.8
Classifier: Programming Language :: Python :: 3.9
Classifier: Operating System :: OS Independent
Requires-Dist: paramiko (==2.8.1)
